[{"description":"Cump Obor","value":"220","category":"Food","dateTime":"02/10/2019","uniqueId":1549818018303},{"description":"Asoc Relatii","value":"20","category":"Personal","dateTime":"02/10/2019","uniqueId":1549818101515},{"description":"Chirie feb","value":"910","category":"Living","dateTime":"02/10/2019","uniqueId":1549818190841},{"description":"Cioco ","value":"16.6","category":"Food","dateTime":"02/10/2019","uniqueId":1549818271811},{"description":"Cump Mega","value":"94","category":"Food","dateTime":"02/10/2019","uniqueId":1549818427766},{"description":"Cartela Vodafone","value":"39.6","category":"Utilities","dateTime":"02/10/2019","uniqueId":1549818534915},{"description":"Spaga instalator","value":"20","category":"Living","dateTime":"02/10/2019","uniqueId":1549818591855},{"description":"Rds net x2","value":"75","category":"Utilities","dateTime":"02/10/2019","uniqueId":1549818640623},{"description":"Apa + cioco\t","value":"20","category":"Food","dateTime":"02/10/2019","uniqueId":1549818675480},{"description":"Factura curent x2","value":"58.5","category":"Living","dateTime":"02/10/2019","uniqueId":1549818761944},{"description":"Cump Carrefour","value":"31","category":"Food","dateTime":"02/10/2019","uniqueId":1549818835708},{"description":"Di.fm","value":"19","category":"Personal","dateTime":"02/10/2019","uniqueId":1549818859046},{"description":"cartela metrou","value":"70","category":"Transport","dateTime":"02/10/2019","uniqueId":1549819035480},{"description":"Cump Obor","value":"330","category":"Food","dateTime":"02/10/2019","uniqueId":1549819194181},{"description":"Aparat de ras","value":"133","category":"Tech","dateTime":"02/17/2019","uniqueId":1550417359385},{"description":"Cump Mega","value":"146","category":"Food","dateTime":"02/17/2019","uniqueId":1550417521625},{"description":"Cump Carrefour","value":"9","category":"Food","dateTime":"02/17/2019","uniqueId":1550417605176},{"description":"Branzeturi Bio","value":"63","category":"Food","dateTime":"02/17/2019","uniqueId":1550417687198},{"description":"7 card","value":"125","category":"Sport","dateTime":"02/17/2019","uniqueId":1550417746189},{"description":"Cioco + apa birou","value":"10","category":"Food","dateTime":"02/17/2019","uniqueId":1550417817558},{"description":"Cump Obor","value":"80","category":"Food","dateTime":"02/17/2019","uniqueId":1550418040300},{"description":"Supra shooz","value":"320","category":"Clothes","dateTime":"2/23/2019","uniqueId":1550920885552},{"description":"Cump Mega","value":"80","category":"Food","dateTime":"2/23/2019","uniqueId":1550921811115},{"description":"Intretinere + apometre x2\n","value":"577","category":"Living","dateTime":"2/23/2019","uniqueId":1550922195582},{"description":"Medium monthly","value":"23","category":"Personal","dateTime":"2/23/2019","uniqueId":1550922295500},{"description":"Apa 10L","value":"9","category":"Food","dateTime":"2/23/2019","uniqueId":1550922338878},{"description":"Farm Tei(sapun + spray + Mg)","value":"34","category":"Personal","dateTime":"2/23/2019","uniqueId":1550922449285},{"description":"Placinta ","value":"4","category":"Food","dateTime":"2/23/2019","uniqueId":1550922582369},{"description":"Cumparaturi Obor","value":"178","category":"Food","dateTime":"2/23/2019","uniqueId":1550929842423},{"description":"Cumparaturi Mega","value":"110","category":"Food","dateTime":"02/26/2019","uniqueId":1551523854300},{"description":"Farm. Tei (test candida + dop urechi)","value":"25","category":"Health","dateTime":"02/27/2019","uniqueId":1551524938578},{"description":"Farm Tei(Mg + Spray + Sapun)","value":"34","category":"Health","dateTime":"02/27/2019","uniqueId":1551525141046},{"description":"Apa birou","value":"6","category":"Food","dateTime":"02/28/2019","uniqueId":1551525465384},{"description":"Martisor colege","value":"10","category":"Personal","dateTime":"02/28/2019","uniqueId":1551525559847},{"description":"cafea birou","value":"3","category":"Food","dateTime":"02/26/2019","uniqueId":1551525597690},{"description":"Asoc relatii","value":"20","category":"Personal","dateTime":"03/01/2019","uniqueId":1551525739385},{"description":"Apa 10L","value":"9","category":"Food","dateTime":"03/02/2019","uniqueId":1551525830853},{"description":"Ulei cocos 1L","value":"60","category":"Food","dateTime":"03/02/2019","uniqueId":1551525910858},{"description":"Farm Tei(Dopuri urechi + det vase)","value":"32.5","category":"Health","dateTime":"03/02/2019","uniqueId":1551526069142},{"description":"Internet","value":"37.43","category":"Utilities","dateTime":"01/05/2019","id":1546664508230},{"description":"Asociatia pentru relatii","value":"20","category":"Personal","dateTime":"01/05/2019","id":1546664555179},{"description":"Cumparaturi Mega","value":"205.47","category":"Food","dateTime":"01/05/2019","id":1546664601573},{"description":"Cumparaturi Obor","value":"220","category":"Food","dateTime":"01/09/2019","id":1547056181244},{"description":"Diferenta cartela metrou","value":"27","category":"Transport","dateTime":"01/09/2019","id":1547056250207},{"description":"Drum revelion","value":"50","category":"Transport","dateTime":"01/09/2019","id":1547056314870},{"description":"Fotbal","value":"22","category":"Sport","dateTime":"01/09/2019","id":1547056348188},{"description":"Chirie Ianuarie - apometre","value":"892","category":"Living","dateTime":"01/09/2019","id":1547056561659},{"description":"Ceaiuri + miere Obor","value":"21.6","category":"Food","dateTime":"01/09/2019","id":1547056603026},{"description":"Cumparaturi Mega","value":"58.26","category":"Food","dateTime":"01/09/2019","id":1547056636523},{"description":"Cartela Vodafone","value":"38.78","category":"Living","dateTime":"01/09/2019","id":1547061254935},{"description":"DI.fm","value":"19.35","category":"Personal","dateTime":"01/09/2019","id":1547061285103},{"description":"7Card","value":"125","category":"Sport","dateTime":"01/09/2019","id":1547061316460},{"description":"Cumparaturi Obor","value":"260","category":"Food","dateTime":"01/13/2019","id":1547382855547},{"description":"Intretinere Octombrie","value":"163","category":"Living","dateTime":"01/13/2019","id":1547382918859},{"description":"Mi Fitness Band","value":"90","category":"Tech","dateTime":"01/13/2019","id":1547382987519},{"description":"Imprimanta Canon","value":"225","category":"Tech","dateTime":"01/13/2019","id":1547383023945},{"description":"Cumparaturi Mega","value":"45","category":"Food","dateTime":"01/18/2019","id":1547840928346},{"description":"Detergent vase","value":"7.3","category":"Living","dateTime":"01/18/2019","id":1547841039956},{"description":"orez + apa Carefour","value":"18","category":"Food","dateTime":"01/18/2019","id":1547841093577},{"description":"Fotbal","value":"35","category":"Sport","dateTime":"01/18/2019","id":1547842919482},{"description":"Cumparaturi mega 10 ian","value":"62","category":"Food","dateTime":"01/18/2019","id":1547843056246},{"description":"Cumparaturi Obor","value":"260","category":"Food","dateTime":"01/19/2019","id":1547916378626},{"description":"Ulei cod + alge","value":"40","category":"Food","dateTime":"01/19/2019","id":1547916509438},{"description":"sapun + detergent vase + sampon + pasta de dinti + periuta de dinti Farmacia Tei","value":"119","category":"Personal","dateTime":"01/19/2019","id":1547916724922},{"description":"Airsoft","value":"105","category":"Sport","dateTime":"01/20/2019","id":1547989536110},{"description":"10L apa plata","value":"9","category":"Food","dateTime":"01/20/2019","id":1547989716563},{"description":"TP for my bumhole","value":"7","category":"Personal","dateTime":"01/20/2019","id":1547989754435},{"description":"Medium subscription","value":"23","category":"Personal","dateTime":"01/20/2019","id":1547989833581},{"description":"Cumparaturi Mega ","value":"101","category":"Food","dateTime":"01/21/2019","id":1548102068482},{"description":"Kindle","value":"579","category":"Tech","dateTime":"01/26/2019","id":1548507558077},{"description":"Mortal Kombat present for little brother","value":"286","category":"Personal","dateTime":"01/26/2019","id":1548507805614},{"description":"Fotbal","value":"27","category":"Sport","dateTime":"01/26/2019","id":1548508120252},{"description":"Apa plata 10L","value":"8.6","category":"Food","dateTime":"01/26/2019","id":1548508233964},{"description":"Cumparaturi Obor ","value":"210","category":"Food","dateTime":"01/26/2019","id":1548508338682},{"description":"cumparaturi Karefour","value":"20","category":"Food","dateTime":"01/31/2019","id":1548965569791},{"description":"cumparaturi Mega","value":"89","category":"Food","dateTime":"01/31/2019","id":1548965626715},{"description":"apa + cafea ","value":"9","category":"Food","dateTime":"01/31/2019","id":1548965641976},{"description":"ochelari vedere","value":"37","category":"Personal","dateTime":"01/31/2019","id":1548965747718},{"description":"substanta gandaci","value":"40","category":"Living","dateTime":"01/31/2019","id":1548965763125},{"description":"Husa telefon","value":"40","category":"Tech","dateTime":"01/31/2019","id":1548965793757},{"description":"Cump Kaufland","value":"210","category":"Food","dateTime":"03/03/2019","uniqueId":1552215300662},{"description":"Chirie Martie","value":"867","category":"Living","dateTime":"03/04/2019","uniqueId":1552215366650},{"description":"Cump Mega","value":"154","category":"Food","dateTime":"03/05/2019","uniqueId":1552215397663},{"description":"Portofel","value":"160","category":"Clothes","dateTime":"03/08/2019","uniqueId":1552215762393},{"description":"Acumulator extern","value":"104","category":"Tech","dateTime":"03/08/2019","uniqueId":1552215953442},{"description":"Cartus imprimanta","value":"106","category":"Tech","dateTime":"03/08/2019","uniqueId":1552216011763},{"description":"Cartela metrou","value":"70","category":"Transport","dateTime":"03/08/2019","uniqueId":1552216080105},{"description":"Cump Carrefour","value":"33","category":"Food","dateTime":"03/10/2019","uniqueId":1552216140252},{"description":"DI.fm","value":"20","category":"Personal","dateTime":"03/10/2019","uniqueId":1552216163887},{"description":"Stila de vin","value":"18","category":"Personal","dateTime":"03/03/2019","uniqueId":1552216214108},{"description":"Cump Kaufland","value":"263","category":"Food","dateTime":"03/09/2019","uniqueId":1552216358964},{"description":"Vin + tirbuson","value":"43","category":"Personal","dateTime":"03/09/2019","uniqueId":1552216381132},{"description":"Film + nachos","value":"46","category":"Personal","dateTime":"03/08/2019","uniqueId":1552216607496},{"description":"Cadou colege 8 mar","value":"10","category":"Personal","dateTime":"03/08/2019","uniqueId":1552216650940},{"description":"diverse birou","value":"10","category":"Food","dateTime":"03/06/2019","uniqueId":1552216768258},{"description":"plimbare parc ","value":"40","category":"Personal","dateTime":"03/10/2019","uniqueId":1552722609571},{"description":"Cump Mega","value":"155.5","category":"Food","dateTime":"03/13/2019","uniqueId":1552722681488},{"description":"7Card","value":"129","category":"Sport","dateTime":"03/15/2019","uniqueId":1552722761456},{"description":"Cart Vodafone","value":"40","category":"Utilities","dateTime":"03/16/2019","uniqueId":1552723048779},{"description":"cump Kaufland","value":"192","category":"Food","dateTime":"03/17/2019","uniqueId":1552937108906},{"description":"cump Carrefour","value":"35","category":"Food","dateTime":"03/18/2019","uniqueId":1552937190385},{"description":"2xcurent(feb+mar)","value":"54","category":"Utilities","dateTime":"03/18/2019","uniqueId":1552939831815},{"description":"cump Mega","value":"101","category":"Food","dateTime":"03/20/2019","uniqueId":1553349483424},{"description":"apa + batoane proteice","value":"10","category":"Food","dateTime":"03/21/2019","uniqueId":1553349536448},{"description":"Medium sub","value":"23","category":"Tech","dateTime":"03/22/2019","uniqueId":1553349592963},{"description":"cadou colega","value":"10","category":"Personal","dateTime":"03/19/2019","uniqueId":1553349838332},{"description":"carrefour cioco + apa","value":"23","category":"Food","dateTime":"03/23/2019","uniqueId":1553353543840},{"description":"cump kaufland","value":"198.5","category":"Food","dateTime":"03/24/2019","uniqueId":1553447816160},{"description":"chirie ian","value":"311","category":"Utilities","dateTime":"03/25/2019","uniqueId":1553630744900},{"description":"cump Mega ","value":"57","category":"Food","dateTime":"03/25/2019","uniqueId":1553631397311},{"description":"sticla vin","value":"17.5","category":"Personal","dateTime":"03/24/2019","uniqueId":1553631443939},{"description":"tuns","value":"30","category":"Personal","dateTime":"03/27/2019","uniqueId":1553714215705},{"description":"apa + cioco + legume ciorbix","value":"19.5","category":"Food","dateTime":"03/30/2019","uniqueId":1553936645279},{"description":"cotlet berbecut","value":"27","category":"Food","dateTime":"03/29/2019","uniqueId":1553936709818},{"description":"apa + baton proteic ","value":"5.5","category":"Food","dateTime":"03/29/2019","uniqueId":1553936741684}]